rqstr/__init__.py
rqstr/__main__.py
rqstr/_version.py
rqstr/const.py
rqstr/resources/example-collection.yml
rqstr/schema/__init__.py
rqstr/schema/asserts.py
rqstr/schema/auth.py
rqstr/schema/headers.py
rqstr/schema/output.py
rqstr/schema/request.py
rqstr_cli-0.1.0.dist-info/METADATA
rqstr_cli-0.1.0.dist-info/WHEEL
rqstr_cli-0.1.0.dist-info/entry_points.txt
rqstr_cli-0.1.0.dist-info/top_level.txt
rqstr_cli-0.1.0.dist-info/RECORD
