Metadata-Version: 2.4
Name: rqstr-cli
Version: 0.1.0
Summary: Add your description here
Requires-Python: >=3.9
Requires-Dist: cyclopts>=3.24.0
Requires-Dist: httpx>=0.28.1
Requires-Dist: loguru>=0.7.3
Requires-Dist: piny>=1.1.0
Requires-Dist: pydantic>=2.11.4
Requires-Dist: pydantic-settings>=2.11.0
